mycpu/Z16DataMemory.v
module Z16DataMemory(
    input wire i_clk,
    
    input wire [15:0] i_addr,
    input wire i_wen,
    input wire [15:0] i_data,
    output wire [15:0] o_data
);

reg [15:0] mem[1023:0];

assign o_data = mem[i_addr[10:1]];

always @(posedge i_clk) begin
    if(i_wen) begin
        mem[i_addr[10:1]] <= i_data;
    end
end

endmodule

mycpu/Z16ALU.v
module Z16ALU(
  input  wire   [15:0]  i_data_a,
  input  wire   [15:0]  i_data_b,
  input  wire   [3:0]   i_ctrl,
  output wire   [15:0]  o_data
);

  assign o_data = alu(i_data_a, i_data_b, i_ctrl);

  function [15:0] alu;
    input [15:0]    i_data_a;
    input [15:0]    i_data_b;
    input [3:0]     i_ctrl;

    begin
      case(i_ctrl)
        4'h0 : alu  = i_data_b + i_data_a;
        4'h1 : alu  = i_data_b - i_data_a;
        4'h2 : alu  = i_data_b * i_data_a;
        4'h3 : alu  = i_data_b / i_data_a;
        4'h4 : alu  = i_data_b | i_data_a;
        4'h5 : alu  = i_data_b & i_data_a;
        4'h6 : alu  = i_data_b ^ i_data_a;
        4'h7 : alu  = i_data_a << i_data_a;
        4'h8 : alu  = i_data_a >> i_data_a;
        default: alu = i_data_b + i_data_a;
      endcase
    end
  endfunction

endmodule

mycpu/tutorial_Z16/Z16RegisterFile.v
module Z16RegisterFile(
    input wire i_clk,
    
    input wire [3:0] i_rs1_addr,
    output wire [15:0] o_rs1_data,

    input wire [3:0] i_rs2_addr,
    output wire [15:0] o_rs2_data,

    input wire [3:0] i_rd_addr,
    input wire i_rd_wen,
    input wire [15:0] i_rd_data
);

reg [15:0] mem[15:0];

assign o_rs1_data = (i_rs1_addr == 4'h0) ? 16'h0000 : mem[i_rs1_addr];
assign o_rs2_data = (i_rs2_addr == 4'h0) ? 16'h0000 : mem[i_rs2_addr];

always @(posedge i_clk) begin
    if(i_rd_wen) begin
        mem[i_rd_addr] <= i_rd_data;
    end else begin
        mem[i_rd_addr] <= mem[i_rd_addr];
    end
end

endmodule

mycpu/Z16Decoder.v
module Z16Decoder(
    input wire [15:0] i_instr,
    output wire [3:0] o_opcode,
    output wire [3:0] o_rd_addr,
    output wire [3:0] o_rs1_addr,
    output wire[15:0] o_imm,
    output wire o_rd_wen, // 出力レジスタ書き込み有効: 1
    output wire o_mem_wen, // メモリ書き込み有効: 0
    output wire [3:0] o_alu_ctrl
);

assign o_opcode = i_instr[3:0];
assign o_rd_addr = i_instr[7:4];
assign o_rs1_addr = i_instr[11:8];
assign o_imm = get_imm(i_instr);

function [15:0] get_imm;
    input [15:0] i_instr;
begin
    case(i_instr[3:0])
    4'hA: get_imm ={{12{i_instr[15]}}, i_instr[15:12]};
    default: get_imm = 16'h0000;
    endcase
end
endfunction

function get_rd_wen;
    input [15:0] i_instr;
begin
    if(4'hA == i_instr[3:0])begin
        get_rd_wen = 1'b1;
    end else begin
        get_rd_wen = 1'b0;
    end
end
endfunction

function get_mem_wen;
    input [15:0] i_instr;
begin
    if(4'hA == i_instr[3:0])begin
        get_mem_wen = 1'b0;
    end else begin
        get_mem_wen = 1'b0;
    end
end
endfunction

function [3:0] get_alu_ctrl;
    input [15:0] i_instr;
begin
    if(4'hA == i_instr[3:0])begin
        get_alu_ctrl = 4'h0;
    end else begin
        get_alu_ctrl = 4'h0;
    end
end
endfunction


endmodule

mycpu/Z16InstrMemory.v
module Z16InstrMemory(
    input wire [15:0] i_addr,
    output wire [15:0] o_instr
);

wire [15:0] mem[4:0];

assign o_instr = mem[i_addr[15:1]];

assign mem[0] = 16'h406A; // LOAD 4 ZR G2 
assign mem[1] = 16'h0000;
assign mem[2] = 16'h0000;
assign mem[3] = 16'h008A; // LOAD 0 ZR G4
assign mem[4] = 16'h0000;

endmodule

mycpu/tutorial_Z16/Z16CPU.v
module Z16CPU(
  input  wire   i_clk,
  input  wire   i_rst
);

  // Program Counter
  reg   [15:0]  r_pc;

  wire  [15:0]  w_instr;
  wire [3:0]    w_rd_addr;
  wire [3:0]    w_rs1_addr;
  wire [15:0]   w_imm;
  wire          w_rd_wen;
  wire          w_mem_wen;
  wire [3:0]    w_alu_ctrl;

  wire [15:0]   w_rs1_data;

  wire [15:0]   w_alu_data;
  wire [15:0]   w_mem_rdata;

  always @(posedge i_clk) begin
    if(i_rst) begin
      r_pc  <= 16'h0000;
    end else begin
      r_pc  <= r_pc + 16'h0002;
    end
  end

  Z16InstrMemory InstrMem(
    .i_addr     (r_pc   ),
    .o_instr    (w_instr)
  );

  Z16Decoder Decoder(
    .i_instr    (w_instr    ),
    .o_rd_addr  (w_rd_addr  ),
    .o_rs1_addr (w_rs1_addr ),
    .o_imm      (w_imm      ),
    .o_rd_wen   (w_rd_wen   ),
    .o_mem_wen  (w_mem_wen  ),
    .o_alu_ctrl (w_alu_ctrl )
  );

  Z16RegisterFile RegFile(
    .i_clk      (i_clk      ),
    .i_rs1_addr (w_rs1_addr ),
    .o_rs1_data (w_rs1_data ),
    .i_rs2_addr (),
    .o_rs2_data (),
    .i_rd_data  (w_mem_rdata),
    .i_rd_addr  (w_rd_addr  ),
    .i_rd_wen   (w_rd_wen   )
  );

  Z16ALU ALU(
    .i_data_a   (w_rs1_data ),
    .i_data_b   (w_imm      ),
    .i_ctrl     (w_alu_ctrl ),
    .o_data     (w_alu_data )
  );

  Z16DataMemory DataMem(
    .i_clk  (i_clk      ),
    .i_addr (w_alu_data ),
    .i_wen  (w_mem_wen  ),
    .i_data (),
    .o_data (w_mem_rdata)
  );

endmodule

mycpu/tutorial_Z16/Z16CPU_tb.v
module Z16CPU_tb;

  reg i_clk = 1'b0;
  reg i_rst = 1'b0;

  always #1 begin
    i_clk <= ~i_clk;
  end

  initial begin
    $dumpfile("wave.vcd");
    $dumpvars(0, Z16CPU_tb);
  end

  Z16CPU CPU(
    .i_clk  (i_clk  ),
    .i_rst  (i_rst  )
  );

  initial begin
    // リセット
    i_rst   = 1'b1;
    #2
    // リセットを落とし、実行開始
    i_rst   = 1'b0;
    #100
    $finish;
  end

endmodule

mycpu/wave.vcd
$date
	Fri Jan 02 15:08:42 2026
$end
$version
	Icarus Verilog
$end
$timescale
	1s
$end
$scope module Z16CPU_tb $end
$var reg 1 ! i_clk $end
$var reg 1 " i_rst $end
$scope module CPU $end
$var wire 1 ! i_clk $end
$var wire 1 " i_rst $end
$var wire 4 # w_alu_ctrl [3:0] $end
$var wire 1 $ w_mem_wen $end
$var wire 1 % w_rd_wen $end
$var wire 16 & w_rs1_data [15:0] $end
$var wire 4 ' w_rs1_addr [3:0] $end
$var wire 4 ( w_rd_addr [3:0] $end
$var wire 16 ) w_mem_rdata [15:0] $end
$var wire 16 * w_instr [15:0] $end
$var wire 16 + w_imm [15:0] $end
$var wire 16 , w_alu_data [15:0] $end
$var reg 16 - r_pc [15:0] $end
$scope module ALU $end
$var wire 4 . i_ctrl [3:0] $end
$var wire 16 / o_data [15:0] $end
$var wire 16 0 i_data_b [15:0] $end
$var wire 16 1 i_data_a [15:0] $end
$scope function alu $end
$var reg 4 2 i_ctrl [3:0] $end
$var reg 16 3 i_data_a [15:0] $end
$var reg 16 4 i_data_b [15:0] $end
$upscope $end
$upscope $end
$scope module DataMem $end
$var wire 16 5 i_addr [15:0] $end
$var wire 1 ! i_clk $end
$var wire 16 6 i_data [15:0] $end
$var wire 1 $ i_wen $end
$var wire 16 7 o_data [15:0] $end
$upscope $end
$scope module Decoder $end
$var wire 4 8 o_alu_ctrl [3:0] $end
$var wire 1 $ o_mem_wen $end
$var wire 1 % o_rd_wen $end
$var wire 4 9 o_rs1_addr [3:0] $end
$var wire 4 : o_rd_addr [3:0] $end
$var wire 4 ; o_opcode [3:0] $end
$var wire 16 < o_imm [15:0] $end
$var wire 16 = i_instr [15:0] $end
$scope function get_alu_ctrl $end
$var reg 16 > i_instr [15:0] $end
$upscope $end
$scope function get_imm $end
$var reg 16 ? i_instr [15:0] $end
$upscope $end
$scope function get_mem_wen $end
$var reg 16 @ i_instr [15:0] $end
$upscope $end
$scope function get_rd_wen $end
$var reg 16 A i_instr [15:0] $end
$upscope $end
$upscope $end
$scope module InstrMem $end
$var wire 16 B i_addr [15:0] $end
$var wire 16 C o_instr [15:0] $end
$upscope $end
$scope module RegFile $end
$var wire 1 ! i_clk $end
$var wire 4 D i_rd_addr [3:0] $end
$var wire 16 E i_rd_data [15:0] $end
$var wire 1 % i_rd_wen $end
$var wire 4 F i_rs1_addr [3:0] $end
$var wire 4 G i_rs2_addr [3:0] $end
$var wire 16 H o_rs2_data [15:0] $end
$var wire 16 I o_rs1_data [15:0] $end
$upscope $end
$upscope $end
$upscope $end
$enddefinitions $end
$comment Show the parameter values. $end
$dumpall
$end
#0
$dumpvars
bx I
bx H
bz G
bx F
bx E
bx D
bx C
bx B
bx A
bx @
bx ?
bx >
bx =
b0 <
bx ;
bx :
bx 9
bz 8
bx 7
bz 6
bx 5
b0 4
bx 3
bz 2
bx 1
b0 0
bx /
bz .
bx -
bx ,
b0 +
bx *
bx )
bx (
bx '
bx &
z%
z$
bz #
1"
0!
$end
#1
b100 ,
b100 /
b100 5
b100 4
b0 3
b0 &
b0 1
b0 I
b100 +
b100 0
b100 <
b100000001101010 ?
b0 '
b0 9
b0 F
b110 (
b110 :
b110 D
b1010 ;
b100000001101010 *
b100000001101010 =
b100000001101010 C
b0 -
b0 B
1!
#2
0!
0"
#3
b0 ,
b0 /
b0 5
b0 4
b0 +
b0 0
b0 <
b0 ?
b0 (
b0 :
b0 D
b0 ;
b0 *
b0 =
b0 C
b10 -
b10 B
1!
#4
0!
#5
b100 -
b100 B
1!
#6
0!
#7
b10001010 ?
b1000 (
b1000 :
b1000 D
b1010 ;
b10001010 *
b10001010 =
b10001010 C
b110 -
b110 B
1!
#8
0!
#9
b0 ?
b0 (
b0 :
b0 D
b0 ;
b0 *
b0 =
b0 C
b1000 -
b1000 B
1!
#10
0!
#11
bx ,
bx /
bx 5
bx 3
bx &
bx 1
bx I
bx ?
bx '
bx 9
bx F
bx (
bx :
bx D
bx ;
bx *
bx =
bx C
b1010 -
b1010 B
1!
#12
0!
#13
b1100 -
b1100 B
1!
#14
0!
#15
b1110 -
b1110 B
1!
#16
0!
#17
b10000 -
b10000 B
1!
#18
0!
#19
b10010 -
b10010 B
1!
#20
0!
#21
b10100 -
b10100 B
1!
#22
0!
#23
b10110 -
b10110 B
1!
#24
0!
#25
b11000 -
b11000 B
1!
#26
0!
#27
b11010 -
b11010 B
1!
#28
0!
#29
b11100 -
b11100 B
1!
#30
0!
#31
b11110 -
b11110 B
1!
#32
0!
#33
b100000 -
b100000 B
1!
#34
0!
#35
b100010 -
b100010 B
1!
#36
0!
#37
b100100 -
b100100 B
1!
#38
0!
#39
b100110 -
b100110 B
1!
#40
0!
#41
b101000 -
b101000 B
1!
#42
0!
#43
b101010 -
b101010 B
1!
#44
0!
#45
b101100 -
b101100 B
1!
#46
0!
#47
b101110 -
b101110 B
1!
#48
0!
#49
b110000 -
b110000 B
1!
#50
0!
#51
b110010 -
b110010 B
1!
#52
0!
#53
b110100 -
b110100 B
1!
#54
0!
#55
b110110 -
b110110 B
1!
#56
0!
#57
b111000 -
b111000 B
1!
#58
0!
#59
b111010 -
b111010 B
1!
#60
0!
#61
b111100 -
b111100 B
1!
#62
0!
#63
b111110 -
b111110 B
1!
#64
0!
#65
b1000000 -
b1000000 B
1!
#66
0!
#67
b1000010 -
b1000010 B
1!
#68
0!
#69
b1000100 -
b1000100 B
1!
#70
0!
#71
b1000110 -
b1000110 B
1!
#72
0!
#73
b1001000 -
b1001000 B
1!
#74
0!
#75
b1001010 -
b1001010 B
1!
#76
0!
#77
b1001100 -
b1001100 B
1!
#78
0!
#79
b1001110 -
b1001110 B
1!
#80
0!
#81
b1010000 -
b1010000 B
1!
#82
0!
#83
b1010010 -
b1010010 B
1!
#84
0!
#85
b1010100 -
b1010100 B
1!
#86
0!
#87
b1010110 -
b1010110 B
1!
#88
0!
#89
b1011000 -
b1011000 B
1!
#90
0!
#91
b1011010 -
b1011010 B
1!
#92
0!
#93
b1011100 -
b1011100 B
1!
#94
0!
#95
b1011110 -
b1011110 B
1!
#96
0!
#97
b1100000 -
b1100000 B
1!
#98
0!
#99
b1100010 -
b1100010 B
1!
#100
0!
#101
b1100100 -
b1100100 B
1!
