mycpu/RISC-V_Anvil/blink.v
module SOC (
    input  CLK,
    input  RESET,
    output [4:0] LEDS,
    input  RXD,
    output TXD
);

reg [4:0] count = 0;
always @(posedge CLK) begin
    count <= count + 1;
end

assign LEDS = count;
endmodule

mycpu/RISC-V_Anvil/blink_tb.v
`timescale 1ns/1ps

module bench;
    reg CLK;
    wire RESET = 0;
    wire [4:0] LEDS;
    reg RXD = 1'b0;
    wire TXD;

    SOC uut(
        .CLK (CLK),
        .RESET (RESET),
        .LEDS (LEDS),
        .RXD (RXD),
        .TXD (TXD)
    );

    initial begin
        $dumpfile("wave.vcd");
        $dumpvars(0, bench);
    end

    always #1 CLK = ~CLK;

    reg [4:0] prev_LEDS = 0;
    initial begin
        CLK = 0;
        forever begin
            #1 CLK = ~CLK;
            if(LEDS != prev_LEDS) begin
                $display("LEDS = %b", LEDS);
            end
            prev_LEDS = LEDS;
        end
    end
endmodule

mycpu/RISC-V_Anvil/wave.vcd
$date
	Sun Jan 04 01:01:50 2026
$end
$version
	Icarus Verilog
$end
$timescale
	1ps
$end
$scope module bench $end
$var wire 1 ! RESET $end
$var wire 1 " TXD $end
$var wire 5 # LEDS [4:0] $end
$var reg 1 $ CLK $end
$var reg 1 % RXD $end
$var reg 5 & prev_LEDS [4:0] $end
$scope module uut $end
$var wire 1 $ CLK $end
$var wire 5 ' LEDS [4:0] $end
$var wire 1 ! RESET $end
$var wire 1 % RXD $end
$var wire 1 " TXD $end
$var reg 5 ( count [4:0] $end
$upscope $end
$upscope $end
$enddefinitions $end
$comment Show the parameter values. $end
$dumpall
$end
#0
$dumpvars
b0 (
b0 '
b0 &
0%
0$
b0 #
z"
0!
$end
#1000
b1 #
b1 '
b1 (
0$
#2000
b10 #
b10 '
b10 (
b1 &
0$
#3000
b11 #
b11 '
b11 (
b10 &
0$
#4000
b100 #
b100 '
b100 (
b11 &
0$
#5000
b101 #
b101 '
b101 (
b100 &
0$
#6000
b110 #
b110 '
b110 (
b101 &
0$
#7000
b111 #
b111 '
b111 (
b110 &
0$
#8000
b1000 #
b1000 '
b1000 (
b111 &
0$
#9000
b1001 #
b1001 '
b1001 (
b1000 &
0$
#10000
b1010 #
b1010 '
b1010 (
b1001 &
0$
#11000
b1011 #
b1011 '
b1011 (
b1010 &
0$
#12000
b1100 #
b1100 '
b1100 (
b1011 &
0$
#13000
b1101 #
b1101 '
b1101 (
b1100 &
0$
#14000
b1110 #
b1110 '
b1110 (
b1101 &
0$
#15000
b1111 #
b1111 '
b1111 (
b1110 &
0$
#16000
b10000 #
b10000 '
b10000 (
b1111 &
0$
#17000
b10001 #
b10001 '
b10001 (
b10000 &
0$
#18000
b10010 #
b10010 '
b10010 (
b10001 &
0$
#19000
b10011 #
b10011 '
b10011 (
b10010 &
0$
#20000
b10100 #
b10100 '
b10100 (
b10011 &
0$
#21000
b10101 #
b10101 '
b10101 (
b10100 &
0$
#22000
b10110 #
b10110 '
b10110 (
b10101 &
0$
#23000
b10111 #
b10111 '
b10111 (
b10110 &
0$
#24000
b11000 #
b11000 '
b11000 (
b10111 &
0$
#25000
b11001 #
b11001 '
b11001 (
b11000 &
0$
#26000
b11010 #
b11010 '
b11010 (
b11001 &
0$
#27000
b11011 #
b11011 '
b11011 (
b11010 &
0$
#28000
b11100 #
b11100 '
b11100 (
b11011 &
0$
#29000
b11101 #
b11101 '
b11101 (
b11100 &
0$
#30000
b11110 #
b11110 '
b11110 (
b11101 &
0$
#31000
b11111 #
b11111 '
b11111 (
b11110 &
0$
#32000
b0 #
b0 '
b0 (
b11111 &
0$
#33000
b1 #
b1 '
b1 (
b0 &
0$
#34000
b10 #
b10 '
b10 (
b1 &
0$
#35000
b11 #
b11 '
b11 (
b10 &
0$
#36000
b100 #
b100 '
b100 (
b11 &
0$
#37000
b101 #
b101 '
b101 (
b100 &
0$
#38000
b110 #
b110 '
b110 (
b101 &
0$
#39000
b111 #
b111 '
b111 (
b110 &
0$
#40000
b1000 #
b1000 '
b1000 (
b111 &
0$
#41000
b1001 #
b1001 '
b1001 (
b1000 &
0$
#42000
b1010 #
b1010 '
b1010 (
b1001 &
0$
#43000
b1011 #
b1011 '
b1011 (
b1010 &
0$
#44000
b1100 #
b1100 '
b1100 (
b1011 &
0$
#45000
b1101 #
b1101 '
b1101 (
b1100 &
0$
#46000
b1110 #
b1110 '
b1110 (
b1101 &
0$
#47000
b1111 #
b1111 '
b1111 (
b1110 &
0$
#48000
b10000 #
b10000 '
b10000 (
b1111 &
0$
#49000
b10001 #
b10001 '
b10001 (
b10000 &
0$
#50000
b10010 #
b10010 '
b10010 (
b10001 &
0$
#51000
b10011 #
b10011 '
b10011 (
b10010 &
0$
#52000
b10100 #
b10100 '
b10100 (
b10011 &
0$
#53000
b10101 #
b10101 '
b10101 (
b10100 &
0$
#54000
b10110 #
b10110 '
b10110 (
b10101 &
0$
#55000
b10111 #
b10111 '
b10111 (
b10110 &
0$
#56000
b11000 #
b11000 '
b11000 (
b10111 &
0$
#57000
b11001 #
b11001 '
b11001 (
b11000 &
0$
#58000
b11010 #
b11010 '
b11010 (
b11001 &
0$
#59000
b11011 #
b11011 '
b11011 (
b11010 &
0$
#60000
b11100 #
b11100 '
b11100 (
b11011 &
0$
#61000
b11101 #
b11101 '
b11101 (
b11100 &
0$
#62000
b11110 #
b11110 '
b11110 (
b11101 &
0$
#63000
b11111 #
b11111 '
b11111 (
b11110 &
0$
#64000
b0 #
b0 '
b0 (
b11111 &
0$
#65000
b1 #
b1 '
b1 (
b0 &
0$
#66000
b10 #
b10 '
b10 (
b1 &
0$
#67000
b11 #
b11 '
b11 (
b10 &
0$
#68000
b100 #
b100 '
b100 (
b11 &
0$
#69000
b101 #
b101 '
b101 (
b100 &
0$
#70000
b110 #
b110 '
b110 (
b101 &
0$
#71000
b111 #
b111 '
b111 (
b110 &
0$
#72000
b1000 #
b1000 '
b1000 (
b111 &
0$
#73000
b1001 #
b1001 '
b1001 (
b1000 &
0$
#74000
b1010 #
b1010 '
b1010 (
b1001 &
0$
#75000
b1011 #
b1011 '
b1011 (
b1010 &
0$
#76000
b1100 #
b1100 '
b1100 (
b1011 &
0$
#77000
b1101 #
b1101 '
b1101 (
b1100 &
0$
#78000
b1110 #
b1110 '
b1110 (
b1101 &
0$
#79000
b1111 #
b1111 '
b1111 (
b1110 &
0$
#80000
b10000 #
b10000 '
b10000 (
b1111 &
0$
#81000
b10001 #
b10001 '
b10001 (
b10000 &
0$
#82000
b10010 #
b10010 '
b10010 (
b10001 &
0$
#83000
b10011 #
b10011 '
b10011 (
b10010 &
0$
#84000
b10100 #
b10100 '
b10100 (
b10011 &
0$
#85000
b10101 #
b10101 '
b10101 (
b10100 &
0$
#86000
b10110 #
b10110 '
b10110 (
b10101 &
0$
#87000
b10111 #
b10111 '
b10111 (
b10110 &
0$
#88000
b11000 #
b11000 '
b11000 (
b10111 &
0$
#89000
b11001 #
b11001 '
b11001 (
b11000 &
0$
#90000
b11010 #
b11010 '
b11010 (
b11001 &
0$
#91000
b11011 #
b11011 '
b11011 (
b11010 &
0$
#92000
b11100 #
b11100 '
b11100 (
b11011 &
0$
#93000
b11101 #
b11101 '
b11101 (
b11100 &
0$
#94000
b11110 #
b11110 '
b11110 (
b11101 &
0$
#95000
b11111 #
b11111 '
b11111 (
b11110 &
0$
#96000
b0 #
b0 '
b0 (
b11111 &
0$
#97000
b1 #
b1 '
b1 (
b0 &
0$
#98000
b10 #
b10 '
b10 (
b1 &
0$
#99000
b11 #
b11 '
b11 (
b10 &
0$
#100000
b100 #
b100 '
b100 (
b11 &
0$
#101000
b101 #
b101 '
b101 (
b100 &
0$
#102000
b110 #
b110 '
b110 (
b101 &
0$
#103000
b111 #
b111 '
b111 (
b110 &
0$
#104000
b1000 #
b1000 '
b1000 (
b111 &
0$
#105000
b1001 #
b1001 '
b1001 (
b1000 &
0$
#106000
b1010 #
b1010 '
b1010 (
b1001 &
0$
#107000
b1011 #
b1011 '
b1011 (
b1010 &
0$
#108000
b1100 #
b1100 '
b1100 (
b1011 &
0$
#109000
b1101 #
b1101 '
b1101 (
b1100 &
0$
#110000
b1110 #
b1110 '
b1110 (
b1101 &
0$
#111000
b1111 #
b1111 '
b1111 (
b1110 &
0$
#112000
b10000 #
b10000 '
b10000 (
b1111 &
0$
#113000
b10001 #
b10001 '
b10001 (
b10000 &
0$
#114000
b10010 #
b10010 '
b10010 (
b10001 &
0$
#115000
b10011 #
b10011 '
b10011 (
b10010 &
0$
#116000
b10100 #
b10100 '
b10100 (
b10011 &
0$
#117000
b10101 #
b10101 '
b10101 (
b10100 &
0$
#118000
b10110 #
b10110 '
b10110 (
b10101 &
0$
#119000
b10111 #
b10111 '
b10111 (
b10110 &
0$
#120000
b11000 #
b11000 '
b11000 (
b10111 &
0$
#121000
b11001 #
b11001 '
b11001 (
b11000 &
0$
#122000
b11010 #
b11010 '
b11010 (
b11001 &
0$
#123000
b11011 #
b11011 '
b11011 (
b11010 &
0$
#124000
b11100 #
b11100 '
b11100 (
b11011 &
0$
#125000
b11101 #
b11101 '
b11101 (
b11100 &
0$
#126000
b11110 #
b11110 '
b11110 (
b11101 &
0$
#127000
b11111 #
b11111 '
b11111 (
b11110 &
0$
#128000
b0 #
b0 '
b0 (
b11111 &
0$
#129000
b1 #
b1 '
b1 (
b0 &
0$
#130000
b10 #
b10 '
b10 (
b1 &
0$
#131000
b11 #
b11 '
b11 (
b10 &
0$
#132000
b100 #
b100 '
b100 (
b11 &
0$
#133000
b101 #
b101 '
b101 (
b100 &
0$
#134000
b110 #
b110 '
b110 (
b101 &
0$
#135000
b111 #
b111 '
b111 (
b110 &
0$
#136000
b1000 #
b1000 '
b1000 (
b111 &
0$
#137000
b1001 #
b1001 '
b1001 (
b1000 &
0$
#138000
b1010 #
b1010 '
b1010 (
b1001 &
0$
#139000
b1011 #
b1011 '
b1011 (
b1010 &
0$
#140000
b1100 #
b1100 '
b1100 (
b1011 &
0$
#141000
b1101 #
b1101 '
b1101 (
b1100 &
0$
#142000
b1110 #
b1110 '
b1110 (
b1101 &
0$
#143000
b1111 #
b1111 '
b1111 (
b1110 &
0$
#144000
b10000 #
b10000 '
b10000 (
b1111 &
0$
#145000
b10001 #
b10001 '
b10001 (
b10000 &
0$
#146000
b10010 #
b10010 '
b10010 (
b10001 &
0$
#147000
b10011 #
b10011 '
b10011 (
b10010 &
0$
#148000
b10100 #
b10100 '
b10100 (
b10011 &
0$
#149000
b10101 #
b10101 '
b10101 (
b10100 &
0$
#150000
b10110 #
b10110 '
b10110 (
b10101 &
0$
#151000
b10111 #
b10111 '
b10111 (
b10110 &
0$
#152000
b11000 #
b11000 '
b11000 (
b10111 &
0$
#153000
b11001 #
b11001 '
b11001 (
b11000 &
0$
#154000
b11010 #
b11010 '
b11010 (
b11001 &
0$
#155000
b11011 #
b11011 '
b11011 (
b11010 &
0$
#156000
b11100 #
b11100 '
b11100 (
b11011 &
0$
#157000
b11101 #
b11101 '
b11101 (
b11100 &
0$
#158000
b11110 #
b11110 '
b11110 (
b11101 &
0$
#159000
b11111 #
b11111 '
b11111 (
b11110 &
0$
#160000
b0 #
b0 '
b0 (
b11111 &
0$
#161000
b1 #
b1 '
b1 (
b0 &
0$
#162000
b10 #
b10 '
b10 (
b1 &
0$
#163000
b11 #
b11 '
b11 (
b10 &
0$
#164000
b100 #
b100 '
b100 (
b11 &
0$
#165000
b101 #
b101 '
b101 (
b100 &
0$
#166000
b110 #
b110 '
b110 (
b101 &
0$
#167000
b111 #
b111 '
b111 (
b110 &
0$
#168000
b1000 #
b1000 '
b1000 (
b111 &
0$
#169000
b1001 #
b1001 '
b1001 (
b1000 &
0$
#170000
b1010 #
b1010 '
b1010 (
b1001 &
0$
#171000
b1011 #
b1011 '
b1011 (
b1010 &
0$
#172000
b1100 #
b1100 '
b1100 (
b1011 &
0$
#173000
b1101 #
b1101 '
b1101 (
b1100 &
0$
#174000
b1110 #
b1110 '
b1110 (
b1101 &
0$
#175000
b1111 #
b1111 '
b1111 (
b1110 &
0$
#176000
b10000 #
b10000 '
b10000 (
b1111 &
0$
#177000
b10001 #
b10001 '
b10001 (
b10000 &
0$
#178000
b10010 #
b10010 '
b10010 (
b10001 &
0$
#179000
b10011 #
b10011 '
b10011 (
b10010 &
0$
#180000
b10100 #
b10100 '
b10100 (
b10011 &
0$
#181000
b10101 #
b10101 '
b10101 (
b10100 &
0$
#182000
b10110 #
b10110 '
b10110 (
b10101 &
0$
#183000
b10111 #
b10111 '
b10111 (
b10110 &
0$
#184000
b11000 #
b11000 '
b11000 (
b10111 &
0$
#185000
b11001 #
b11001 '
b11001 (
b11000 &
0$
#186000
b11010 #
b11010 '
b11010 (
b11001 &
0$
#187000
b11011 #
b11011 '
b11011 (
b11010 &
0$
#188000
b11100 #
b11100 '
b11100 (
b11011 &
0$
#189000
b11101 #
b11101 '
b11101 (
b11100 &
0$
#190000
b11110 #
b11110 '
b11110 (
b11101 &
0$
#191000
b11111 #
b11111 '
b11111 (
b11110 &
0$
#192000
b0 #
b0 '
b0 (
b11111 &
0$
#193000
b1 #
b1 '
b1 (
b0 &
0$
#194000
b10 #
b10 '
b10 (
b1 &
0$
#195000
b11 #
b11 '
b11 (
b10 &
0$
#196000
b100 #
b100 '
b100 (
b11 &
0$
#197000
b101 #
b101 '
b101 (
b100 &
0$
#198000
b110 #
b110 '
b110 (
b101 &
0$
#199000
b111 #
b111 '
b111 (
b110 &
0$
#200000
b1000 #
b1000 '
b1000 (
b111 &
0$
#201000
b1001 #
b1001 '
b1001 (
b1000 &
0$
#202000
b1010 #
b1010 '
b1010 (
b1001 &
0$
#203000
b1011 #
b1011 '
b1011 (
b1010 &
0$
#204000
b1100 #
b1100 '
b1100 (
b1011 &
0$
#205000
b1101 #
b1101 '
b1101 (
b1100 &
0$
#206000
b1110 #
b1110 '
b1110 (
b1101 &
0$
#207000
b1111 #
b1111 '
b1111 (
b1110 &
0$
#208000
b10000 #
b10000 '
b10000 (
b1111 &
0$
#209000
b10001 #
b10001 '
b10001 (
b10000 &
0$
#210000
b10010 #
b10010 '
b10010 (
b10001 &
0$
#211000
b10011 #
b10011 '
b10011 (
b10010 &
0$
#212000
b10100 #
b10100 '
b10100 (
b10011 &
0$
#213000
b10101 #
b10101 '
b10101 (
b10100 &
0$
#214000
b10110 #
b10110 '
b10110 (
b10101 &
0$
#215000
b10111 #
b10111 '
b10111 (
b10110 &
0$
#216000
b11000 #
b11000 '
b11000 (
b10111 &
0$
#217000
b11001 #
b11001 '
b11001 (
b11000 &
0$
#218000
b11010 #
b11010 '
b11010 (
b11001 &
0$
#219000
b11011 #
b11011 '
b11011 (
b11010 &
0$
#220000
b11100 #
b11100 '
b11100 (
b11011 &
0$
#221000
b11101 #
b11101 '
b11101 (
b11100 &
0$
#222000
b11110 #
b11110 '
b11110 (
b11101 &
0$
#223000
b11111 #
b11111 '
b11111 (
b11110 &
0$
#224000
b0 #
b0 '
b0 (
b11111 &
0$
#225000
b1 #
b1 '
b1 (
b0 &
0$
#226000
b10 #
b10 '
b10 (
b1 &
0$
#227000
b11 #
b11 '
b11 (
b10 &
0$
#228000
b100 #
b100 '
b100 (
b11 &
0$
#229000
b101 #
b101 '
b101 (
b100 &
0$
#230000
b110 #
b110 '
b110 (
b101 &
0$
#231000
b111 #
b111 '
b111 (
b110 &
0$
#232000
b1000 #
b1000 '
b1000 (
b111 &
0$
#233000
b1001 #
b1001 '
b1001 (
b1000 &
0$
#234000
b1010 #
b1010 '
b1010 (
b1001 &
0$
#235000
b1011 #
b1011 '
b1011 (
b1010 &
0$
#236000
b1100 #
b1100 '
b1100 (
b1011 &
0$
#237000
b1101 #
b1101 '
b1101 (
b1100 &
0$
#238000
b1110 #
b1110 '
b1110 (
b1101 &
0$
#239000
b1111 #
b1111 '
b1111 (
b1110 &
0$
#240000
b10000 #
b10000 '
b10000 (
b1111 &
0$
#241000
b10001 #
b10001 '
b10001 (
b10000 &
0$
#242000
b10010 #
b10010 '
b10010 (
b10001 &
0$
#243000
b10011 #
b10011 '
b10011 (
b10010 &
0$
#244000
b10100 #
b10100 '
b10100 (
b10011 &
0$
#245000
b10101 #
b10101 '
b10101 (
b10100 &
0$
#246000
b10110 #
b10110 '
b10110 (
b10101 &
0$
#247000
b10111 #
b10111 '
b10111 (
b10110 &
0$
#248000
b11000 #
b11000 '
b11000 (
b10111 &
0$
#249000
b11001 #
b11001 '
b11001 (
b11000 &
0$
#250000
b11010 #
b11010 '
b11010 (
b11001 &
0$
#251000
b11011 #
b11011 '
b11011 (
b11010 &
0$
#252000
b11100 #
b11100 '
b11100 (
b11011 &
0$
#253000
b11101 #
b11101 '
b11101 (
b11100 &
0$
#254000
b11110 #
b11110 '
b11110 (
b11101 &
0$
#255000
b11111 #
b11111 '
b11111 (
b11110 &
0$
#256000
b0 #
b0 '
b0 (
b11111 &
0$
#257000
b1 #
b1 '
b1 (
b0 &
0$
#258000
b10 #
b10 '
b10 (
b1 &
0$
#259000
b11 #
b11 '
b11 (
b10 &
0$
#260000
b100 #
b100 '
b100 (
b11 &
0$
#261000
b101 #
b101 '
b101 (
b100 &
0$
#262000
b110 #
b110 '
b110 (
b101 &
0$
#263000
b111 #
b111 '
b111 (
b110 &
0$
#264000
b1000 #
b1000 '
b1000 (
b111 &
0$
#265000
b1001 #
b1001 '
b1001 (
b1000 &
0$
#266000
b1010 #
b1010 '
b1010 (
b1001 &
0$
#267000
b1011 #
b1011 '
b1011 (
b1010 &
0$
#268000
b1100 #
b1100 '
b1100 (
b1011 &
0$
#269000
b1101 #
b1101 '
b1101 (
b1100 &
0$
#270000
b1110 #
b1110 '
b1110 (
b1101 &
0$
#271000
b1111 #
b1111 '
b1111 (
b1110 &
0$
#272000
b10000 #
b10000 '
b10000 (
b1111 &
0$
#273000
b10001 #
b10001 '
b10001 (
b10000 &
0$
#274000
b10010 #
b10010 '
b10010 (
b10001 &
0$
#275000
b10011 #
b10011 '
b10011 (
b10010 &
0$
#276000
b10100 #
b10100 '
b10100 (
b10011 &
0$
#277000
b10101 #
b10101 '
b10101 (
b10100 &
0$
#278000
b10110 #
b10110 '
b10110 (
b10101 &
0$
#279000
b10111 #
b10111 '
b10111 (
b10110 &
0$
#280000
b11000 #
b11000 '
b11000 (
b10111 &
0$
#281000
b11001 #
b11001 '
b11001 (
b11000 &
0$
#282000
b11010 #
b11010 '
b11010 (
b11001 &
0$
#283000
b11011 #
b11011 '
b11011 (
b11010 &
0$
#284000
b11100 #
b11100 '
b11100 (
b11011 &
0$
#285000
b11101 #
b11101 '
b11101 (
b11100 &
0$
#286000
b11110 #
b11110 '
b11110 (
b11101 &
0$
#287000
b11111 #
b11111 '
b11111 (
b11110 &
0$
#288000
b0 #
b0 '
b0 (
b11111 &
0$
#289000
b1 #
b1 '
b1 (
b0 &
0$
#290000
b10 #
b10 '
b10 (
b1 &
0$
#291000
b11 #
b11 '
b11 (
b10 &
0$
#292000
b100 #
b100 '
b100 (
b11 &
0$
#293000
b101 #
b101 '
b101 (
b100 &
0$
#294000
b110 #
b110 '
b110 (
b101 &
0$
#295000
b111 #
b111 '
b111 (
b110 &
0$
#296000
b1000 #
b1000 '
b1000 (
b111 &
0$
#297000
b1001 #
b1001 '
b1001 (
b1000 &
0$
#298000
b1010 #
b1010 '
b1010 (
b1001 &
0$
#299000
b1011 #
b1011 '
b1011 (
b1010 &
0$
#300000
b1100 #
b1100 '
b1100 (
b1011 &
0$
#301000
b1101 #
b1101 '
b1101 (
b1100 &
0$
#302000
b1110 #
b1110 '
b1110 (
b1101 &
0$
#303000
b1111 #
b1111 '
b1111 (
b1110 &
0$
#304000
b10000 #
b10000 '
b10000 (
b1111 &
0$
#305000
b10001 #
b10001 '
b10001 (
b10000 &
0$
#306000
b10010 #
b10010 '
b10010 (
b10001 &
0$
#307000
b10011 #
b10011 '
b10011 (
b10010 &
0$
#308000
b10100 #
b10100 '
b10100 (
b10011 &
0$
#309000
b10101 #
b10101 '
b10101 (
b10100 &
0$
#310000
b10110 #
b10110 '
b10110 (
b10101 &
0$
#311000
b10111 #
b10111 '
b10111 (
b10110 &
0$
#312000
b11000 #
b11000 '
b11000 (
b10111 &
0$
#313000
b11001 #
b11001 '
b11001 (
b11000 &
0$
#314000
b11010 #
b11010 '
b11010 (
b11001 &
0$
#315000
b11011 #
b11011 '
b11011 (
b11010 &
0$
#316000
b11100 #
b11100 '
b11100 (
b11011 &
0$
#317000
b11101 #
b11101 '
b11101 (
b11100 &
0$
#318000
b11110 #
b11110 '
b11110 (
b11101 &
0$
#319000
b11111 #
b11111 '
b11111 (
b11110 &
0$
#320000
b0 #
b0 '
b0 (
b11111 &
0$
#321000
b1 #
b1 '
b1 (
b0 &
0$
#322000
b10 #
b10 '
b10 (
b1 &
0$
#323000
b11 #
b11 '
b11 (
b10 &
0$
#324000
b100 #
b100 '
b100 (
b11 &
0$
#325000
b101 #
b101 '
b101 (
b100 &
0$
#326000
b110 #
b110 '
b110 (
b101 &
0$
#327000
b111 #
b111 '
b111 (
b110 &
0$
#328000
b1000 #
b1000 '
b1000 (
b111 &
0$
#329000
b1001 #
b1001 '
b1001 (
b1000 &
0$
#330000
b1010 #
b1010 '
b1010 (
b1001 &
0$
#331000
b1011 #
b1011 '
b1011 (
b1010 &
0$
#332000
b1100 #
b1100 '
b1100 (
b1011 &
0$
#333000
b1101 #
b1101 '
b1101 (
b1100 &
0$
#334000
b1110 #
b1110 '
b1110 (
b1101 &
0$
#335000
b1111 #
b1111 '
b1111 (
b1110 &
0$
#336000
b10000 #
b10000 '
b10000 (
b1111 &
0$
#337000
b10001 #
b10001 '
b10001 (
b10000 &
0$
#338000
b10010 #
b10010 '
b10010 (
b10001 &
0$
#339000
b10011 #
b10011 '
b10011 (
b10010 &
0$
#340000
b10100 #
b10100 '
b10100 (
b10011 &
0$
#341000
b10101 #
b10101 '
b10101 (
b10100 &
0$
#342000
b10110 #
b10110 '
b10110 (
b10101 &
0$
#343000
b10111 #
b10111 '
b10111 (
b10110 &
0$
#344000
b11000 #
b11000 '
b11000 (
b10111 &
0$
#345000
b11001 #
b11001 '
b11001 (
b11000 &
0$
#346000
b11010 #
b11010 '
b11010 (
b11001 &
0$
#347000
b11011 #
b11011 '
b11011 (
b11010 &
0$
#348000
b11100 #
b11100 '
b11100 (
b11011 &
0$
#349000
b11101 #
b11101 '
b11101 (
b11100 &
0$
#350000
b11110 #
b11110 '
b11110 (
b11101 &
0$
#351000
b11111 #
b11111 '
b11111 (
b11110 &
0$
#352000
b0 #
b0 '
b0 (
b11111 &
0$
#353000
b1 #
b1 '
b1 (
b0 &
0$
#354000
b10 #
b10 '
b10 (
b1 &
0$
#355000
b11 #
b11 '
b11 (
b10 &
0$
#356000
b100 #
b100 '
b100 (
b11 &
0$
#357000
b101 #
b101 '
b101 (
b100 &
0$
#358000
b110 #
b110 '
b110 (
b101 &
0$
#359000
b111 #
b111 '
b111 (
b110 &
0$
#360000
b1000 #
b1000 '
b1000 (
b111 &
0$
#361000
b1001 #
b1001 '
b1001 (
b1000 &
0$
#362000
b1010 #
b1010 '
b1010 (
b1001 &
0$
#363000
b1011 #
b1011 '
b1011 (
b1010 &
0$
#364000
b1100 #
b1100 '
b1100 (
b1011 &
0$
#365000
b1101 #
b1101 '
b1101 (
b1100 &
0$
#366000
b1110 #
b1110 '
b1110 (
b1101 &
0$
#367000
b1111 #
b1111 '
b1111 (
b1110 &
0$
#368000
b10000 #
b10000 '
b10000 (
b1111 &
0$
#369000
b10001 #
b10001 '
b10001 (
b10000 &
0$
#370000
b10010 #
b10010 '
b10010 (
b10001 &
0$
#371000
b10011 #
b10011 '
b10011 (
b10010 &
0$
#372000
b10100 #
b10100 '
b10100 (
b10011 &
0$
#373000
b10101 #
b10101 '
b10101 (
b10100 &
0$
#374000
b10110 #
b10110 '
b10110 (
b10101 &
0$
#375000
b10111 #
b10111 '
b10111 (
b10110 &
0$
#376000
b11000 #
b11000 '
b11000 (
b10111 &
0$
#377000
b11001 #
b11001 '
b11001 (
b11000 &
0$
#378000
b11010 #
b11010 '
b11010 (
b11001 &
0$
#379000
b11011 #
b11011 '
b11011 (
b11010 &
0$
#380000
b11100 #
b11100 '
b11100 (
b11011 &
0$
#381000
b11101 #
b11101 '
b11101 (
b11100 &
0$
#382000
b11110 #
b11110 '
b11110 (
b11101 &
0$
#383000
b11111 #
b11111 '
b11111 (
b11110 &
0$
#384000
b0 #
b0 '
b0 (
b11111 &
0$
#385000
b1 #
b1 '
b1 (
b0 &
0$
#386000
b10 #
b10 '
b10 (
b1 &
0$
#387000
b11 #
b11 '
b11 (
b10 &
0$
#388000
b100 #
b100 '
b100 (
b11 &
0$
#389000
b101 #
b101 '
b101 (
b100 &
0$
#390000
b110 #
b110 '
b110 (
b101 &
0$
#391000
b111 #
b111 '
b111 (
b110 &
0$
#392000
b1000 #
b1000 '
b1000 (
b111 &
0$
#393000
b1001 #
b1001 '
b1001 (
b1000 &
0$
#394000
b1010 #
b1010 '
b1010 (
b1001 &
0$
#395000
b1011 #
b1011 '
b1011 (
b1010 &
0$
#396000
b1100 #
b1100 '
b1100 (
b1011 &
0$
#397000
b1101 #
b1101 '
b1101 (
b1100 &
0$
#398000
b1110 #
b1110 '
b1110 (
b1101 &
0$
#399000
b1111 #
b1111 '
b1111 (
b1110 &
0$
#400000
b10000 #
b10000 '
b10000 (
b1111 &
0$
#401000
b10001 #
b10001 '
b10001 (
b10000 &
0$
#402000
b10010 #
b10010 '
b10010 (
b10001 &
0$
#403000
b10011 #
b10011 '
b10011 (
b10010 &
0$
#404000
b10100 #
b10100 '
b10100 (
b10011 &
0$
#405000
b10101 #
b10101 '
b10101 (
b10100 &
0$
#406000
b10110 #
b10110 '
b10110 (
b10101 &
0$
#407000
b10111 #
b10111 '
b10111 (
b10110 &
0$
#408000
b11000 #
b11000 '
b11000 (
b10111 &
0$
#409000
b11001 #
b11001 '
b11001 (
b11000 &
0$
#410000
b11010 #
b11010 '
b11010 (
b11001 &
0$
#411000
b11011 #
b11011 '
b11011 (
b11010 &
0$
#412000
b11100 #
b11100 '
b11100 (
b11011 &
0$
#413000
b11101 #
b11101 '
b11101 (
b11100 &
0$
#414000
b11110 #
b11110 '
b11110 (
b11101 &
0$
#415000
b11111 #
b11111 '
b11111 (
b11110 &
0$
#416000
b0 #
b0 '
b0 (
b11111 &
0$
#417000
b1 #
b1 '
b1 (
b0 &
0$
#418000
b10 #
b10 '
b10 (
b1 &
0$
#419000
b11 #
b11 '
b11 (
b10 &
0$
#420000
b100 #
b100 '
b100 (
b11 &
0$
#421000
b101 #
b101 '
b101 (
b100 &
0$
#422000
b110 #
b110 '
b110 (
b101 &
0$
#423000
b111 #
b111 '
b111 (
b110 &
0$
#424000
b1000 #
b1000 '
b1000 (
b111 &
0$
#425000
b1001 #
b1001 '
b1001 (
b1000 &
0$
#426000
b1010 #
b1010 '
b1010 (
b1001 &
0$
#427000
b1011 #
b1011 '
b1011 (
b1010 &
0$
#428000
b1100 #
b1100 '
b1100 (
b1011 &
0$
#429000
b1101 #
b1101 '
b1101 (
b1100 &
0$
#430000
b1110 #
b1110 '
b1110 (
b1101 &
0$
#431000
b1111 #
b1111 '
b1111 (
b1110 &
0$
#432000
b10000 #
b10000 '
b10000 (
b1111 &
0$
#433000
b10001 #
b10001 '
b10001 (
b10000 &
0$
#434000
b10010 #
b10010 '
b10010 (
b10001 &
0$
#435000
b10011 #
b10011 '
b10011 (
b10010 &
0$
#436000
b10100 #
b10100 '
b10100 (
b10011 &
0$
#437000
b10101 #
b10101 '
b10101 (
b10100 &
0$
#438000
b10110 #
b10110 '
b10110 (
b10101 &
0$
#439000
b10111 #
b10111 '
b10111 (
b10110 &
0$
#440000
b11000 #
b11000 '
b11000 (
b10111 &
0$
#441000
b11001 #
b11001 '
b11001 (
b11000 &
0$
#442000
b11010 #
b11010 '
b11010 (
b11001 &
0$
#443000
b11011 #
b11011 '
b11011 (
b11010 &
0$
#444000
b11100 #
b11100 '
b11100 (
b11011 &
0$
#445000
b11101 #
b11101 '
b11101 (
b11100 &
0$
#446000
b11110 #
b11110 '
b11110 (
b11101 &
0$
#447000
b11111 #
b11111 '
b11111 (
b11110 &
0$
#448000
b0 #
b0 '
b0 (
b11111 &
0$
#449000
b1 #
b1 '
b1 (
b0 &
0$
#450000
b10 #
b10 '
b10 (
b1 &
0$
#451000
b11 #
b11 '
b11 (
b10 &
0$
#452000
b100 #
b100 '
b100 (
b11 &
0$
#453000
b101 #
b101 '
b101 (
b100 &
0$
#454000
b110 #
b110 '
b110 (
b101 &
0$
#455000
b111 #
b111 '
b111 (
b110 &
0$
#456000
b1000 #
b1000 '
b1000 (
b111 &
0$
#457000
b1001 #
b1001 '
b1001 (
b1000 &
0$
#458000
b1010 #
b1010 '
b1010 (
b1001 &
0$
#459000
b1011 #
b1011 '
b1011 (
b1010 &
0$
#460000
b1100 #
b1100 '
b1100 (
b1011 &
0$
#461000
b1101 #
b1101 '
b1101 (
b1100 &
0$
#462000
b1110 #
b1110 '
b1110 (
b1101 &
0$
#463000
b1111 #
b1111 '
b1111 (
b1110 &
0$
#464000
b10000 #
b10000 '
b10000 (
b1111 &
0$
#465000
b10001 #
b10001 '
b10001 (
b10000 &
0$
#466000
b10010 #
b10010 '
b10010 (
b10001 &
0$
#467000
b10011 #
b10011 '
b10011 (
b10010 &
0$
#468000
b10100 #
b10100 '
b10100 (
b10011 &
0$
#469000
b10101 #
b10101 '
b10101 (
b10100 &
0$
#470000
b10110 #
b10110 '
b10110 (
b10101 &
0$
#471000
b10111 #
b10111 '
b10111 (
b10110 &
0$
